remip_client/__init__.py
remip_client/_version.py
remip_client/environment.py
remip_client/http_client.py
remip_client/solver.py
remip_client-0.3.3.dist-info/METADATA
remip_client-0.3.3.dist-info/WHEEL
remip_client-0.3.3.dist-info/RECORD
