Metadata-Version: 2.4
Name: remip-client
Version: 0.3.3
Summary: A client library for the MIP Solver API
Author-email: ohtaman <ohtamans@gmail.com>
Requires-Python: >=3.11
Requires-Dist: pulp
Requires-Dist: requests
